LICENSE
MANIFEST.in
README.md
setup.py
chamber/__init__.py
chamber/config.py
chamber/patch.py
chamber/shortcuts.py
chamber/version.py
chamber/commands/__init__.py
chamber/contrib/auth_token/backends.py
chamber/exceptions/__init__.py
chamber/formatters/__init__.py
chamber/forms/__init__.py
chamber/forms/fields.py
chamber/forms/validators.py
chamber/importers/__init__.py
chamber/locale/cs/LC_MESSAGES/django.mo
chamber/locale/cs/LC_MESSAGES/django.po
chamber/management/__init__.py
chamber/management/commands/__init__.py
chamber/management/commands/initdata.py
chamber/management/commands/makemessages.py
chamber/models/__init__.py
chamber/models/base.py
chamber/models/batch_iterator.py
chamber/models/changed_fields.py
chamber/models/comparator.py
chamber/models/dispatchers.py
chamber/models/fields.py
chamber/models/handlers.py
chamber/models/signals.py
chamber/models/humanized_helpers/__init__.py
chamber/multidomains/__init__.py
chamber/multidomains/domain.py
chamber/multidomains/urlresolvers.py
chamber/multidomains/auth/__init__.py
chamber/multidomains/auth/backends.py
chamber/multidomains/auth/middleware.py
chamber/storages/__init__.py
chamber/storages/boto3.py
chamber/utils/__init__.py
chamber/utils/datastructures.py
chamber/utils/datetimes.py
chamber/utils/decorators.py
chamber/utils/forms.py
chamber/utils/http.py
chamber/utils/json.py
chamber/utils/logging.py
chamber/utils/tqdm.py
chamber/utils/transaction.py
chamber/utils/migrations/__init__.py
chamber/utils/migrations/fixtures.py
django_chamber.egg-info/PKG-INFO
django_chamber.egg-info/SOURCES.txt
django_chamber.egg-info/dependency_links.txt
django_chamber.egg-info/requires.txt
django_chamber.egg-info/top_level.txt
example/__init__.py
example/manage.py
example/dj/__init__.py
example/dj/backend_urls.py
example/dj/frontend_urls.py
example/dj/wsgi.py
example/dj/apps/__init__.py
example/dj/apps/test_chamber/__init__.py
example/dj/apps/test_chamber/handlers.py
example/dj/apps/test_chamber/importers.py
example/dj/apps/test_chamber/models.py
example/dj/apps/test_chamber/views.py
example/dj/apps/test_chamber/management/__init__.py
example/dj/apps/test_chamber/management/commands/__init__.py
