Metadata-Version: 2.1
Name: django-chamber
Version: 0.6.17
Summary: Utilities library meant as a complement to django-is-core.
Home-page: http://github.com/druids/django-chamber
Author: Lubos Matl, Oskar Hollmann
Author-email: matllubos@gmail.com, oskar@hollmann.me
License: UNKNOWN
Platform: UNKNOWN
Classifier: Development Status :: 4 - Beta
Classifier: Environment :: Web Environment
Classifier: Intended Audience :: Developers
Classifier: License :: OSI Approved :: GNU Library or Lesser General Public License (LGPL)
Classifier: Operating System :: OS Independent
Classifier: Programming Language :: Python
Classifier: Programming Language :: Python :: 3.6
Classifier: Programming Language :: Python :: 3.7
Classifier: Programming Language :: Python :: 3.8
Classifier: Programming Language :: Python :: 3.9
Classifier: Programming Language :: Python :: 3.10
Classifier: Programming Language :: Python :: 3.11
Classifier: Framework :: Django
Requires-Python: >=3.6
Provides-Extra: boto3storage
